setup.py
wxAnyThread/__init__.py
wxAnyThread.egg-info/PKG-INFO
wxAnyThread.egg-info/SOURCES.txt
wxAnyThread.egg-info/dependency_links.txt
wxAnyThread.egg-info/top_level.txt
