Metadata-Version: 1.0
Name: wxAnyThread
Version: 0.1.2
Summary: Allow wxPython object methods to be called from any thread.
Home-page: http://pypi.python.org/pypi/wxAnyThread/
Author: Ryan Kelly
Author-email: ryan@rfk.id.au
License: Public Domain
Keywords: wxPython threading
Platform: UNKNOWN
